subscribe_manager/__init__.py
subscribe_manager/common/__init__.py
subscribe_manager/common/config_util.py
subscribe_manager/common/log_util.py
subscribe_manager/config/__init__.py
subscribe_manager/config/settings.py
subscribe_manager/constant.py
subscribe_manager/database/__init__.py
subscribe_manager/database/db_manager.py
subscribe_manager/main.py
subscribe_manager/service/__init__.py
subscribe_manager/service/base.py
subscribe_manager/service/subscribe_manager.py
subscribe_manager/static/database/sql/ddl/subscribe_manager.sql
subscribe_manager/static/database/sql/dml/delete.sql
subscribe_manager/static/database/sql/dml/insert.sql
subscribe_manager/static/database/sql/dml/query.sql
subscribe_manager/static/database/sql/dml/update.sql
subscribe_manager/static/template/surfboard.template
subscribe_manager/static/template/surge.template
subscribe_manager-0.3.3.dist-info/METADATA
subscribe_manager-0.3.3.dist-info/WHEEL
subscribe_manager-0.3.3.dist-info/entry_points.txt
subscribe_manager-0.3.3.dist-info/RECORD
