Metadata-Version: 2.3
Name: subscribe-manager
Version: 0.3.3
Summary: 订阅代理工具，统一管理订阅，定时下载并存储订阅信息，自动进行订阅转换，并提供代理服务
License: MIT
Author: modestme
Author-email: lowkeymodestme@gmail.com
Requires-Python: >=3.11
Classifier: Development Status :: 4 - Beta
Classifier: Intended Audience :: Developers
Classifier: Intended Audience :: System Administrators
Classifier: Topic :: Internet :: Proxy Servers
Classifier: Topic :: Utilities
Classifier: License :: OSI Approved :: MIT License
Classifier: Programming Language :: Python :: 3.11
Classifier: Operating System :: OS Independent
Requires-Dist: aiohttp (>=3.10.10,<4.0.0)
Requires-Dist: apscheduler (>=3.10.4,<4.0.0)
Requires-Dist: colorama (>=0.4.6,<0.5.0)
Requires-Dist: fastapi (>=0.115.2,<0.116.0)
Requires-Dist: nest-asyncio (>=1.6.0,<2.0.0)
Requires-Dist: pydantic-settings (>=2.6.0,<3.0.0)
Requires-Dist: pyyaml (>=6.0.2,<7.0.0)
Requires-Dist: uvicorn (>=0.31.1,<0.32.0)
